spotdl_romanized_lyrics/.idea/.gitignore
spotdl_romanized_lyrics/.idea/inspectionProfiles/profiles_settings.xml
spotdl_romanized_lyrics/.idea/inspectionProfiles/Project_Default.xml
spotdl_romanized_lyrics/.idea/misc.xml
spotdl_romanized_lyrics/.idea/modules.xml
spotdl_romanized_lyrics/.idea/spotdl(romanized-lyrics).iml
spotdl_romanized_lyrics/.idea/vcs.xml
spotdl_romanized_lyrics/__init__.py
spotdl_romanized_lyrics/__main__.py
spotdl_romanized_lyrics/_version.py
spotdl_romanized_lyrics/console/__init__.py
spotdl_romanized_lyrics/console/download.py
spotdl_romanized_lyrics/console/entry_point.py
spotdl_romanized_lyrics/console/meta.py
spotdl_romanized_lyrics/console/save.py
spotdl_romanized_lyrics/console/sync.py
spotdl_romanized_lyrics/console/web.py
spotdl_romanized_lyrics/download/__init__.py
spotdl_romanized_lyrics/download/downloader.py
spotdl_romanized_lyrics/download/progress_handler.py
spotdl_romanized_lyrics/providers/__init__.py
spotdl_romanized_lyrics/providers/audio/__init__.py
spotdl_romanized_lyrics/providers/audio/base.py
spotdl_romanized_lyrics/providers/audio/youtube.py
spotdl_romanized_lyrics/providers/audio/ytmusic.py
spotdl_romanized_lyrics/providers/lyrics/__init__.py
spotdl_romanized_lyrics/providers/lyrics/azlyrics.py
spotdl_romanized_lyrics/providers/lyrics/base.py
spotdl_romanized_lyrics/providers/lyrics/genius.py
spotdl_romanized_lyrics/providers/lyrics/musixmatch.py
spotdl_romanized_lyrics/providers/translate/__init__.py
spotdl_romanized_lyrics/providers/translate/base.py
spotdl_romanized_lyrics/providers/translate/lyricstranslate.py
spotdl_romanized_lyrics/types/__init__.py
spotdl_romanized_lyrics/types/album.py
spotdl_romanized_lyrics/types/artist.py
spotdl_romanized_lyrics/types/playlist.py
spotdl_romanized_lyrics/types/saved.py
spotdl_romanized_lyrics/types/song.py
spotdl_romanized_lyrics/utils/__init__.py
spotdl_romanized_lyrics/utils/archive.py
spotdl_romanized_lyrics/utils/arguments.py
spotdl_romanized_lyrics/utils/config.py
spotdl_romanized_lyrics-0.0.6.dist-info/entry_points.txt
spotdl_romanized_lyrics-0.0.6.dist-info/LICENSE
spotdl_romanized_lyrics-0.0.6.dist-info/METADATA
spotdl_romanized_lyrics-0.0.6.dist-info/WHEEL
spotdl_romanized_lyrics-0.0.6.dist-info/RECORD
