Metadata-Version: 2.1
Name: spotdl-romanized-lyrics
Version: 0.0.6
Summary: Download your Spotify playlists and songs along with album art and metadata
Home-page: https://github.com/aeska4444/spotify-downloader.git
License: MIT
Author: aeska4444
Requires-Python: >=3.7.2,<3.12
Classifier: Intended Audience :: End Users/Desktop
Classifier: License :: OSI Approved :: MIT License
Classifier: Programming Language :: Python
Classifier: Programming Language :: Python :: 3
Classifier: Programming Language :: Python :: 3.8
Classifier: Programming Language :: Python :: 3.9
Classifier: Programming Language :: Python :: 3.10
Classifier: Programming Language :: Python :: 3.11
Classifier: Programming Language :: Python :: 3
Classifier: Programming Language :: Python :: 3 :: Only
Classifier: Programming Language :: Python :: 3.10
Classifier: Programming Language :: Python :: 3.7
Classifier: Programming Language :: Python :: 3.8
Classifier: Programming Language :: Python :: 3.9
Classifier: Topic :: Multimedia
Classifier: Topic :: Multimedia :: Sound/Audio
Classifier: Topic :: Utilities
Requires-Dist: beautifulsoup4 (>=4.11.1,<5.0.0)
Requires-Dist: fastapi (!=0.89.0)
Requires-Dist: mutagen (>=1.46.0,<2.0.0)
Requires-Dist: platformdirs (>=2.6.2,<3.0.0)
Requires-Dist: pydantic (>=1.10.4,<2.0.0)
Requires-Dist: pykakasi (>=2.2.1,<3.0.0)
Requires-Dist: python-slugify (>=7.0.0,<8.0.0)
Requires-Dist: pytube (>=12.1.2,<13.0.0)
Requires-Dist: rapidfuzz (>=2.13.7,<3.0.0)
Requires-Dist: requests (>=2.28.1,<3.0.0)
Requires-Dist: rich (>=13.0.1,<14.0.0)
Requires-Dist: spotipy (>=2.22.0,<3.0.0)
Requires-Dist: syncedlyrics (>=0.2.1,<0.3.0)
Requires-Dist: uvicorn (>=0.20.0,<0.21.0)
Requires-Dist: yt-dlp (>=2023.1.6,<2024.0.0)
Requires-Dist: ytmusicapi (>=0.22.0,<0.23.0) ; python_version < "3.8"
Requires-Dist: ytmusicapi (>=0.24.0,<0.25.0) ; python_version >= "3.8"
Project-URL: Repository, https://github.com/aeska4444/spotify-downloader.git
